nonebot_plugin_colab_novelai/__init__.py
nonebot_plugin_colab_novelai/__meta__.py
nonebot_plugin_colab_novelai/_main.py
nonebot_plugin_colab_novelai/argparsers.py
nonebot_plugin_colab_novelai/config.py
nonebot_plugin_colab_novelai/access/bce.py
nonebot_plugin_colab_novelai/access/colab.py
nonebot_plugin_colab_novelai/access/cpolar.py
nonebot_plugin_colab_novelai/access/naifu.py
nonebot_plugin_colab_novelai/js/keepPageActive.js
nonebot_plugin_colab_novelai/js/objKeySort.js
nonebot_plugin_colab_novelai/js/undefineWebDriver.js
nonebot_plugin_colab_novelai/permissionManager/__init__.py
nonebot_plugin_colab_novelai/permissionManager/cd.py
nonebot_plugin_colab_novelai/permissionManager/nsfw.py
nonebot_plugin_colab_novelai/saveto/__init__.py
nonebot_plugin_colab_novelai/saveto/local.py
nonebot_plugin_colab_novelai/saveto/webdav.py
nonebot_plugin_colab_novelai/utils/__init__.py
nonebot_plugin_colab_novelai/utils/distributed.py
nonebot_plugin_colab_novelai/utils/webdriver.py
nonebot_plugin_colab_novelai-0.2.2.dist-info/LICENSE
nonebot_plugin_colab_novelai-0.2.2.dist-info/METADATA
nonebot_plugin_colab_novelai-0.2.2.dist-info/WHEEL
nonebot_plugin_colab_novelai-0.2.2.dist-info/top_level.txt
nonebot_plugin_colab_novelai-0.2.2.dist-info/RECORD
