Metadata-Version: 2.1
Name: nonebot-plugin-colab-novelai
Version: 0.2.2
Summary: NoneBot2 由Colab驱动的AI作画插件
Home-page: https://github.com/EtherLeaF/nonebot-plugin-colab-novelai
Author: T_EtherLeaF
Author-email: thetapilla@gmail.com
License: UNKNOWN
Keywords: pip,nonebot2,nonebot,nonebot_plugin,NovelAI,Colaboratory,QQ-bot,chatbot
Platform: any
Classifier: Programming Language :: Python :: 3
Classifier: License :: OSI Approved :: MIT License
Classifier: Operating System :: OS Independent
Requires-Python: >=3.8
License-File: LICENSE
Requires-Dist: nonebot2 (>=2.0.0b4)
Requires-Dist: nonebot-adapter-onebot (>=2.1.5)
Requires-Dist: nonebot-plugin-apscheduler (>=0.1.4)
Requires-Dist: httpx (>=0.23.0)
Requires-Dist: asyncer (>=0.0.2)
Requires-Dist: webdav4 (>=0.9.8)
Requires-Dist: selenium (>=4.6.0)
Requires-Dist: selenium-stealth (>=1.0.6)
Requires-Dist: webdriver-manager (>=3.8.4)
Requires-Dist: av (>=10.0.0)
Requires-Dist: pyyaml (>=6.0)
Requires-Dist: packaging (>=21.3)
Requires-Dist: pillow (>=9.3.0)
